odoo/addons/delivery_ups_oca/README.rst
odoo/addons/delivery_ups_oca/__init__.py
odoo/addons/delivery_ups_oca/__manifest__.py
odoo/addons/delivery_ups_oca/data/product_packaging_data.xml
odoo/addons/delivery_ups_oca/doc/rating/Rating Package RESTful Developer Guide.pdf
odoo/addons/delivery_ups_oca/doc/rating/Rating Package Web Service Developer Guide.pdf
odoo/addons/delivery_ups_oca/doc/shipping/Shipping Package RESTful Developer Guide.pdf
odoo/addons/delivery_ups_oca/doc/shipping/Shipping Package Web Service Developer Guide.pdf
odoo/addons/delivery_ups_oca/doc/tracking/Tracking RESTful Developer Guide.pdf
odoo/addons/delivery_ups_oca/doc/tracking/Tracking Web Service Developer Guide.pdf
odoo/addons/delivery_ups_oca/i18n/delivery_ups_oca.pot
odoo/addons/delivery_ups_oca/models/__init__.py
odoo/addons/delivery_ups_oca/models/delivery_carrier.py
odoo/addons/delivery_ups_oca/models/product_packaging.py
odoo/addons/delivery_ups_oca/models/stock_picking.py
odoo/addons/delivery_ups_oca/models/ups_request.py
odoo/addons/delivery_ups_oca/readme/CONFIGURE.rst
odoo/addons/delivery_ups_oca/readme/CONTRIBUTORS.rst
odoo/addons/delivery_ups_oca/readme/DESCRIPTION.rst
odoo/addons/delivery_ups_oca/readme/ROADMAP.rst
odoo/addons/delivery_ups_oca/readme/USAGE.rst
odoo/addons/delivery_ups_oca/static/description/icon.png
odoo/addons/delivery_ups_oca/static/description/index.html
odoo/addons/delivery_ups_oca/tests/__init__.py
odoo/addons/delivery_ups_oca/tests/test_delivery_ups.py
odoo/addons/delivery_ups_oca/views/delivery_carrier_view.xml
odoo/addons/delivery_ups_oca/views/stock_picking_view.xml
odoo13_addon_delivery_ups_oca-13.0.2.0.1.dist-info/METADATA
odoo13_addon_delivery_ups_oca-13.0.2.0.1.dist-info/WHEEL
odoo13_addon_delivery_ups_oca-13.0.2.0.1.dist-info/top_level.txt
odoo13_addon_delivery_ups_oca-13.0.2.0.1.dist-info/RECORD
