Metadata-Version: 2.1
Name: odoo13-addon-delivery-ups-oca
Version: 13.0.2.0.1
Summary: Integrate UPS webservice
Home-page: https://github.com/OCA/delivery-carrier
Author: Hunki Enterprises BV, Tecnativa, Odoo Community Association (OCA)
Author-email: support@odoo-community.org
License: AGPL-3
Platform: UNKNOWN
Classifier: Programming Language :: Python
Classifier: Framework :: Odoo
Classifier: Framework :: Odoo :: 13.0
Classifier: License :: OSI Approved :: GNU Affero General Public License v3
Classifier: Development Status :: 5 - Production/Stable
Requires-Python: >=3.5
Requires-Dist: odoo13-addon-delivery-package-number
Requires-Dist: odoo13-addon-delivery-price-method
Requires-Dist: odoo13-addon-delivery-state
Requires-Dist: odoo (<13.1dev,>=13.0a)
